bloggart/__init__.py
bloggart/header.py
bloggart/kernel.py
bloggart/core/__init__.py
bloggart/core/config.py
bloggart/core/database.py
bloggart/core/fileserver.py
bloggart/core/repeater.py
bloggart/core/routes.py
bloggart/core/service.py
bloggart/core/static.py
bloggart/core/uploadserver.py
bloggart/core/utils.py
bloggart-0.1.1.dist-info/LICENSE
bloggart-0.1.1.dist-info/METADATA
bloggart-0.1.1.dist-info/WHEEL
bloggart-0.1.1.dist-info/entry_points.txt
bloggart-0.1.1.dist-info/top_level.txt
bloggart-0.1.1.dist-info/RECORD
