Metadata-Version: 2.1
Name: bloggart
Version: 0.1.1
Summary: building your blog including file server and database
Home-page: https://www.hohohaha.cn
Author: xiabo
Author-email: blcuxiabo@126.com
License: UNKNOWN
Project-URL: Bug Reports, https://gitee.com/xiabo0816/bloggart/issues
Project-URL: Funding, https://donate.pypi.org
Project-URL: Say Thanks!, https://gitee.com/xiabo0816/bloggart/
Project-URL: Source, https://gitee.com/xiabo0816/bloggart/
Keywords: bloggart,setuptools,development
Platform: UNKNOWN
Classifier: Development Status :: 3 - Alpha
Classifier: Intended Audience :: Developers
Classifier: Topic :: Software Development :: Build Tools
Classifier: License :: OSI Approved :: MIT License
Classifier: Programming Language :: Python :: 3
Classifier: Programming Language :: Python :: 3.5
Classifier: Programming Language :: Python :: 3.6
Classifier: Programming Language :: Python :: 3.7
Classifier: Programming Language :: Python :: 3.8
Classifier: Programming Language :: Python :: 3.9
Classifier: Programming Language :: Python :: 3.10
Classifier: Programming Language :: Python :: 3 :: Only
Requires-Python: >=3.5, <4
Requires-Dist: peppercorn
Provides-Extra: dev
Requires-Dist: check-manifest ; extra == 'dev'
Provides-Extra: test
Requires-Dist: coverage ; extra == 'test'
